flying_state_machines/__init__.py
flying_state_machines/classes.py
flying_state_machines-0.1.0.dist-info/METADATA
flying_state_machines-0.1.0.dist-info/WHEEL
flying_state_machines-0.1.0.dist-info/RECORD
