Metadata-Version: 2.1
Name: flying-state-machines
Version: 0.1.0
Summary: The only Finite State Machine library with a Flying Spaghetti Monster serialization format
Project-URL: Homepage, https://github.com/k98kurz/flying-state-machines
Project-URL: Bug Tracker, https://github.com/k98kurz/flying-state-machines/issues
Author-email: k98kurz <k98kurz@gmail.com>
Classifier: Development Status :: 3 - Alpha
Classifier: License :: OSI Approved :: ISC License (ISCL)
Classifier: Operating System :: OS Independent
Classifier: Programming Language :: Python :: 3
Classifier: Topic :: Religion
Classifier: Topic :: Software Development :: Libraries
Requires-Python: >=3.10
